<?xml version="1.0" encoding="utf-8" ?>
<log4net>

  <!-- 공통 패턴: %date [%thread] %message -->
  <!-- Display -->
  <appender name="DisplayLog" type="log4net.Appender.RollingFileAppender">
    <File value=".\LOG\DISPLAY_LOG\DISPLAY" />
    <AppendToFile value="true" />
    <RollingStyle value="Composite" />
    <StaticLogFileName value="false" />
    <DatePattern value='"_"yyyyMMdd_HH".txt"' />
    <MaximumFileSize value="20MB" />
    <MaxSizeRollBackups value="10" />
    <ImmediateFlush value="true" />
    <LockingModel type="log4net.Appender.FileAppender+MinimalLock" />
    <layout type="log4net.Layout.PatternLayout">
      <conversionPattern value="%date [%thread] %message%newline" />
    </layout>
  </appender>

  <!-- System -->
  <appender name="SystemLog" type="log4net.Appender.RollingFileAppender">
    <File value=".\LOG\SYSTEM_LOG\SYSTEM" />
    <AppendToFile value="true" />
    <RollingStyle value="Composite" />
    <StaticLogFileName value="false" />
    <DatePattern value='"_"yyyyMMdd_HH".txt"' />
    <MaximumFileSize value="20MB" />
    <MaxSizeRollBackups value="10" />
    <ImmediateFlush value="true" />
    <LockingModel type="log4net.Appender.FileAppender+MinimalLock" />
    <layout type="log4net.Layout.PatternLayout">
      <conversionPattern value="%date [%thread] %message%newline" />
    </layout>
  </appender>

  <!-- RFID -->
  <appender name="RFIDLog" type="log4net.Appender.RollingFileAppender">
    <File value=".\LOG\RFID_LOG\RFID" />
    <AppendToFile value="true" />
    <RollingStyle value="Composite" />
    <StaticLogFileName value="false" />
    <DatePattern value='"_"yyyyMMdd_HH".txt"' />
    <MaximumFileSize value="20MB" />
    <MaxSizeRollBackups value="10" />
    <ImmediateFlush value="true" />
    <LockingModel type="log4net.Appender.FileAppender+MinimalLock" />
    <layout type="log4net.Layout.PatternLayout">
      <conversionPattern value="%date [%thread] %message%newline" />
    </layout>
  </appender>

  <!-- Distance -->
  <appender name="DistanceLog" type="log4net.Appender.RollingFileAppender">
    <File value=".\LOG\DISTANCE_LOG\DISTANCE" />
    <AppendToFile value="true" />
    <RollingStyle value="Composite" />
    <StaticLogFileName value="false" />
    <DatePattern value='"_"yyyyMMdd_HH".txt"' />
    <MaximumFileSize value="20MB" />
    <MaxSizeRollBackups value="10" />
    <ImmediateFlush value="true" />
    <LockingModel type="log4net.Appender.FileAppender+MinimalLock" />
    <layout type="log4net.Layout.PatternLayout">
      <conversionPattern value="%date [%thread] %message%newline" />
    </layout>
  </appender>

  <!-- Vision -->
  <appender name="VisionLog" type="log4net.Appender.RollingFileAppender">
    <File value=".\LOG\VISION_LOG\VISION" />
    <AppendToFile value="true" />
    <RollingStyle value="Composite" />
    <StaticLogFileName value="false" />
    <DatePattern value='"_"yyyyMMdd_HH".txt"' />
    <MaximumFileSize value="20MB" />
    <MaxSizeRollBackups value="10" />
    <ImmediateFlush value="true" />
    <LockingModel type="log4net.Appender.FileAppender+MinimalLock" />
    <layout type="log4net.Layout.PatternLayout">
      <conversionPattern value="%date [%thread] %message%newline" />
    </layout>
  </appender>

  <!-- BackEnd -->
  <appender name="BackEndLog" type="log4net.Appender.RollingFileAppender">
    <File value=".\LOG\BACKEND_LOG\BACKEND" />
    <AppendToFile value="true" />
    <RollingStyle value="Composite" />
    <StaticLogFileName value="false" />
    <DatePattern value='"_"yyyyMMdd_HH".txt"' />
    <MaximumFileSize value="20MB" />
    <MaxSizeRollBackups value="10" />
    <ImmediateFlush value="true" />
    <LockingModel type="log4net.Appender.FileAppender+MinimalLock" />
    <layout type="log4net.Layout.PatternLayout">
      <conversionPattern value="%date [%thread] %message%newline" />
    </layout>
  </appender>

  <!-- BackEndCurrent -->
  <appender name="BackEndCurrentLog" type="log4net.Appender.RollingFileAppender">
    <File value=".\LOG\BACKEND_CURRENT_LOG\BACKEND_CURRENT" />
    <AppendToFile value="true" />
    <RollingStyle value="Composite" />
    <StaticLogFileName value="false" />
    <DatePattern value='"_"yyyyMMdd_HH".txt"' />
    <MaximumFileSize value="20MB" />
    <MaxSizeRollBackups value="10" />
    <ImmediateFlush value="true" />
    <LockingModel type="log4net.Appender.FileAppender+MinimalLock" />
    <layout type="log4net.Layout.PatternLayout">
      <conversionPattern value="%date [%thread] %message%newline" />
    </layout>
  </appender>

  <!-- Action -->
  <appender name="ActionLog" type="log4net.Appender.RollingFileAppender">
    <File value=".\LOG\ACTION_LOG\ACTION" />
    <AppendToFile value="true" />
    <RollingStyle value="Composite" />
    <StaticLogFileName value="false" />
    <DatePattern value='"_"yyyyMMdd_HH".txt"' />
    <MaximumFileSize value="20MB" />
    <MaxSizeRollBackups value="10" />
    <ImmediateFlush value="true" />
    <LockingModel type="log4net.Appender.FileAppender+MinimalLock" />
    <layout type="log4net.Layout.PatternLayout">
      <conversionPattern value="%date [%thread] %message%newline" />
    </layout>
  </appender>

  <!-- Weight -->
  <appender name="WeightLog" type="log4net.Appender.RollingFileAppender">
    <File value=".\LOG\WEIGHT_LOG\WEIGHT" />
    <AppendToFile value="true" />
    <RollingStyle value="Composite" />
    <StaticLogFileName value="false" />
    <DatePattern value='"_"yyyyMMdd_HH".txt"' />
    <MaximumFileSize value="20MB" />
    <MaxSizeRollBackups value="10" />
    <ImmediateFlush value="true" />
    <LockingModel type="log4net.Appender.FileAppender+MinimalLock" />
    <layout type="log4net.Layout.PatternLayout">
      <conversionPattern value="%date [%thread] %message%newline" />
    </layout>
  </appender>

  <!-- VisionCam -->
  <appender name="VisionCamLog" type="log4net.Appender.RollingFileAppender">
    <File value=".\LOG\VISIONCAM_LOG\VISIONCAM" />
    <AppendToFile value="true" />
    <RollingStyle value="Composite" />
    <StaticLogFileName value="false" />
    <DatePattern value='"_"yyyyMMdd_HH".txt"' />
    <MaximumFileSize value="20MB" />
    <MaxSizeRollBackups value="10" />
    <ImmediateFlush value="true" />
    <LockingModel type="log4net.Appender.FileAppender+MinimalLock" />
    <layout type="log4net.Layout.PatternLayout">
      <conversionPattern value="%date [%thread] %message%newline" />
    </layout>
  </appender>

  <!-- 명명된 로거 매핑 -->
  <logger name="DisplayLogEx"><level value="ALL" /><appender-ref ref="DisplayLog" /></logger>
  <logger name="SystemLogEx"><level value="ALL" /><appender-ref ref="SystemLog" /></logger>
  <logger name="RFIDLogEx"><level value="ALL" /><appender-ref ref="RFIDLog" /></logger>
  <logger name="DistanceLogEx"><level value="ALL" /><appender-ref ref="DistanceLog" /></logger>
  <logger name="VisionLogEx"><level value="ALL" /><appender-ref ref="VisionLog" /></logger>
  <logger name="BackEndLogEx"><level value="ALL" /><appender-ref ref="BackEndLog" /></logger>
  <logger name="BackEndCurrentLogEx"><level value="ALL" /><appender-ref ref="BackEndCurrentLog" /></logger>
  <logger name="ActionLogEx"><level value="ALL" /><appender-ref ref="ActionLog" /></logger>
  <logger name="WeightLogEx"><level value="ALL" /><appender-ref ref="WeightLog" /></logger>
  <logger name="VisionCamLogEx"><level value="ALL" /><appender-ref ref="VisionCamLog" /></logger>

  <!-- 선택: 루트 레벨(미사용) -->
  <root>
    <level value="INFO" />
  </root>

</log4net>
